auto_pypi_uploader/__init__.py
auto_pypi_uploader/pypi_uploader.py
auto_pypi_uploader/setup_file_creator.py
auto_pypi_uploader-1.1.1.3.dist-info/LICENSE
auto_pypi_uploader-1.1.1.3.dist-info/METADATA
auto_pypi_uploader-1.1.1.3.dist-info/WHEEL
auto_pypi_uploader-1.1.1.3.dist-info/top_level.txt
auto_pypi_uploader-1.1.1.3.dist-info/RECORD
