Metadata-Version: 2.1
Name: auto-pypi-uploader
Version: 1.1.1.3
Summary: A program to automate the creation of the 'setup.py' file, changing a pip package's version, & publishing it to PyPi.
Home-page: https://github.com/Huckdirks/auto-pypi-exporter
Author: Huck Dirksmeier
Author-email: Huckdirks@gmail.com
License: MIT
Keywords: PyPi,Pip,setup,setup.py,automation
Classifier: Programming Language :: Python
Classifier: License :: OSI Approved :: MIT License
Classifier: Operating System :: OS Independent
Requires-Python: >=3.0
License-File: LICENSE
Requires-Dist: python-dotenv
Requires-Dist: twine
Requires-Dist: wheel
Requires-Dist: setuptools
